MD-MTL/__init__.py
MD-MTL/evaluations/__init__.py
MD-MTL/functions/MTL_Cluster_Least_L21.py
MD-MTL/functions/MTL_Least_L21.py
MD-MTL/functions/MTL_Logistic_L21.py
MD-MTL/functions/MTL_Softmax_L21.py
MD-MTL/functions/__init__.py
MD-MTL/functions/init_opts.py
MD-MTL/functions/utils.py
MD-MTL/functions/tests/__init__.py
MD-MTL/functions/tests/test_C_Least_L21.py
MD-MTL/functions/tests/test_Least_L21.py
MD-MTL/functions/tests/test_binary_logistic.py
MD-MTL/functions/tests/test_data.py
MD-MTL/functions/tests/test_softmax_L21_hinge.py
MD_MTL/__init__.py
MD_MTL/evaluations/__init__.py
MD_MTL/functions/MTL_Cluster_Least_L21.py
MD_MTL/functions/MTL_Least_L21.py
MD_MTL/functions/MTL_Logistic_L21.py
MD_MTL/functions/MTL_Softmax_L21.py
MD_MTL/functions/__init__.py
MD_MTL/functions/init_opts.py
MD_MTL/functions/utils.py
MD_MTL/functions/tests/__init__.py
MD_MTL/functions/tests/test_C_Least_L21.py
MD_MTL/functions/tests/test_Least_L21.py
MD_MTL/functions/tests/test_binary_logistic.py
MD_MTL/functions/tests/test_data.py
MD_MTL/functions/tests/test_softmax_L21_hinge.py
Vampyr_MTL/__init__.py
Vampyr_MTL/evaluations/__init__.py
Vampyr_MTL/evaluations/utils.py
Vampyr_MTL/functions/MTL_Cluster_Least_L21.py
Vampyr_MTL/functions/MTL_Least_L21.py
Vampyr_MTL/functions/MTL_Logistic_L21.py
Vampyr_MTL/functions/MTL_Softmax_L21.py
Vampyr_MTL/functions/MTL_Softmax_L21_hinge.py
Vampyr_MTL/functions/Ordinal_Logistic_L21.py
Vampyr_MTL/functions/__init__.py
Vampyr_MTL/functions/init_opts.py
Vampyr_MTL/functions/tests/__init__.py
Vampyr_MTL/functions/tests/test_C_Least_L21.py
Vampyr_MTL/functions/tests/test_Least_L21.py
Vampyr_MTL/functions/tests/test_binary_logistic.py
Vampyr_MTL/functions/tests/test_data.py
Vampyr_MTL/functions/tests/test_softmax_L21_hinge.py
MD_MTL-0.0.9.dist-info/LICENSE
MD_MTL-0.0.9.dist-info/METADATA
MD_MTL-0.0.9.dist-info/WHEEL
MD_MTL-0.0.9.dist-info/top_level.txt
MD_MTL-0.0.9.dist-info/RECORD
