Metadata-Version: 2.1
Name: MD-MTL
Version: 0.0.9
Summary: An Ensemble Med-Multi-Task Learning Package
Home-page: https://github.com/Interactive-Media-Lab-Data-Science-Team/Vampyr-MTL
Author: Max Jiang
Author-email: haoyanhy.jiang@mail.utoronto.ca
License: UNKNOWN
Platform: UNKNOWN
Classifier: Programming Language :: Python :: 3
Classifier: License :: OSI Approved :: MIT License
Classifier: Operating System :: OS Independent
Requires-Python: >=3.6
